[
    {
        "nid": "+3HP",
        "name": "Amulette de Long\u00e9vit\u00e9",
        "desc": "-Accessoire-\nConf\u00e8re +3HP quand tenu dans l'inventaire",
        "icon_nid": "{J-Treecko} {Lex Talionis} All Icons",
        "icon_index": [
            0,
            1
        ],
        "components": [
            [
                "stat_change",
                [
                    [
                        "HP",
                        3
                    ]
                ]
            ]
        ]
    }
]